{
  "formatVersion": "1.1",
  "component": {
    "group": "at.crowdware",
    "module": "sms",
    "version": "1.1.0",
    "attributes": {
      "org.gradle.status": "release"
    }
  },
  "createdBy": {
    "gradle": {
      "version": "8.4"
    }
  },
  "variants": [
    {
      "name": "metadataApiElements",
      "attributes": {
        "org.gradle.category": "library",
        "org.gradle.usage": "kotlin-metadata",
        "org.jetbrains.kotlin.platform.type": "common"
      },
      "dependencies": [
        {
          "group": "org.jetbrains.kotlin",
          "module": "kotlin-stdlib",
          "version": {
            "requires": "1.9.20"
          }
        }
      ],
      "files": [
        {
          "name": "sms-1.1.0.jar",
          "url": "sms-1.1.0.jar",
          "size": 12935,
          "sha512": "af0f410c03d9c4509bb52bdffe9ebce284dac81fbf3e3361f957efae0ba0a4f340dae21ef6b92b88718ec388acf6fe498a3652157e7d615d9af0e7ce3107e04c",
          "sha256": "8d28a039b77f6d81ee3472c467e5d2037217783adf02e0fdf9e12f4e9460cf85",
          "sha1": "cd66b94794ccdfd7ef78ea879f52b45217b50b25",
          "md5": "3e0c47690ed8521ecb8a73e4ea4992b3"
        }
      ]
    },
    {
      "name": "metadataSourcesElements",
      "attributes": {
        "org.gradle.category": "documentation",
        "org.gradle.dependency.bundling": "external",
        "org.gradle.docstype": "sources",
        "org.gradle.usage": "kotlin-runtime",
        "org.jetbrains.kotlin.platform.type": "common"
      },
      "files": [
        {
          "name": "sms-1.1.0-sources.jar",
          "url": "sms-1.1.0-sources.jar",
          "size": 19951,
          "sha512": "f748d51b7e1d9a92edeb189c103626e18613bc49b931fb7a93428fe1849e9ffc326e1ed9e02cfe49bffbd560394de710077f15fe41a4e6e96d5a8ac9004e1f4f",
          "sha256": "43fb687b777540415c73908c62e3e447facded0e4b3e257c4282539b477ae789",
          "sha1": "589ff35d82578790e775eafcb2e0558d051831c6",
          "md5": "a67b5e5aee6d4e562cad0a1991ad3de2"
        }
      ]
    },
    {
      "name": "jsApiElements-published",
      "attributes": {
        "org.gradle.category": "library",
        "org.gradle.usage": "kotlin-api",
        "org.jetbrains.kotlin.js.compiler": "ir",
        "org.jetbrains.kotlin.platform.type": "js"
      },
      "available-at": {
        "url": "../../sms-js/1.1.0/sms-js-1.1.0.module",
        "group": "at.crowdware",
        "module": "sms-js",
        "version": "1.1.0"
      }
    },
    {
      "name": "jsRuntimeElements-published",
      "attributes": {
        "org.gradle.category": "library",
        "org.gradle.usage": "kotlin-runtime",
        "org.jetbrains.kotlin.js.compiler": "ir",
        "org.jetbrains.kotlin.platform.type": "js"
      },
      "available-at": {
        "url": "../../sms-js/1.1.0/sms-js-1.1.0.module",
        "group": "at.crowdware",
        "module": "sms-js",
        "version": "1.1.0"
      }
    },
    {
      "name": "jsSourcesElements-published",
      "attributes": {
        "org.gradle.category": "documentation",
        "org.gradle.dependency.bundling": "external",
        "org.gradle.docstype": "sources",
        "org.gradle.usage": "kotlin-runtime",
        "org.jetbrains.kotlin.js.compiler": "ir",
        "org.jetbrains.kotlin.platform.type": "js"
      },
      "available-at": {
        "url": "../../sms-js/1.1.0/sms-js-1.1.0.module",
        "group": "at.crowdware",
        "module": "sms-js",
        "version": "1.1.0"
      }
    },
    {
      "name": "jvmApiElements-published",
      "attributes": {
        "org.gradle.category": "library",
        "org.gradle.libraryelements": "jar",
        "org.gradle.usage": "java-api",
        "org.jetbrains.kotlin.platform.type": "jvm"
      },
      "available-at": {
        "url": "../../sms-jvm/1.1.0/sms-jvm-1.1.0.module",
        "group": "at.crowdware",
        "module": "sms-jvm",
        "version": "1.1.0"
      }
    },
    {
      "name": "jvmRuntimeElements-published",
      "attributes": {
        "org.gradle.category": "library",
        "org.gradle.libraryelements": "jar",
        "org.gradle.usage": "java-runtime",
        "org.jetbrains.kotlin.platform.type": "jvm"
      },
      "available-at": {
        "url": "../../sms-jvm/1.1.0/sms-jvm-1.1.0.module",
        "group": "at.crowdware",
        "module": "sms-jvm",
        "version": "1.1.0"
      }
    },
    {
      "name": "jvmSourcesElements-published",
      "attributes": {
        "org.gradle.category": "documentation",
        "org.gradle.dependency.bundling": "external",
        "org.gradle.docstype": "sources",
        "org.gradle.libraryelements": "jar",
        "org.gradle.usage": "java-runtime",
        "org.jetbrains.kotlin.platform.type": "jvm"
      },
      "available-at": {
        "url": "../../sms-jvm/1.1.0/sms-jvm-1.1.0.module",
        "group": "at.crowdware",
        "module": "sms-jvm",
        "version": "1.1.0"
      }
    }
  ]
}
